LICENSE
MANIFEST.in
README.rst
setup.py
django_embed9.egg-info/PKG-INFO
django_embed9.egg-info/SOURCES.txt
django_embed9.egg-info/dependency_links.txt
django_embed9.egg-info/requires.txt
django_embed9.egg-info/top_level.txt
embed9/__init__.py
embed9/forms.py
embed9/main.py
embed9/urls.py
embed9/utils.py
embed9/views.py
embed9/templates/embed9/code.html
embed9/templates/embed9/form.html
embed9/templates/embed9/loader.js
embed9/templates/embed9/widget.html
embed9/templatetags/__init__.py
embed9/templatetags/embed.py