Metadata-Version: 1.1
Name: django-embed9
Version: 0.1
Summary: Django app that make model objects embeddable on 3rd party websites
Home-page: https://github.com/9dev/django-embed9
Author: 9dev
Author-email: 9devmail@gmail.com
License: MIT License
Platform: UNKNOWN
Classifier: Environment :: Web Environment
Classifier: Framework :: Django
Classifier: Intended Audience :: Developers
Classifier: License :: OSI Approved :: MIT License
Classifier: Operating System :: OS Independent
Classifier: Programming Language :: Python
Classifier: Programming Language :: Python :: 2.7
Classifier: Topic :: Internet :: WWW/HTTP
Classifier: Topic :: Internet :: WWW/HTTP :: Dynamic Content
